Metadata-Version: 2.1
Name: rasa-nlu
Version: 0.15.0
Summary: Rasa NLU a natural language parser for bots
Home-page: https://rasa.com
Author: Rasa Technologies GmbH
Author-email: hi@rasa.com
Maintainer: Tom Bocklisch
Maintainer-email: tom@rasa.com
License: Apache 2.0
Download-URL: https://github.com/RasaHQ/rasa_nlu/archive/0.15.0.tar.gz
Project-URL: Bug Reports, https://github.com/rasahq/rasa_nlu/issues
Project-URL: Source, https://github.com/rasahq/rasa_nlu
Keywords: nlp machine-learning machine-learning-library bot bots botkit rasa conversational-agents conversational-ai chatbotchatbot-framework bot-framework
Platform: UNKNOWN
Classifier: Development Status :: 4 - Beta
Classifier: Intended Audience :: Developers
Classifier: License :: OSI Approved :: Apache Software License
Classifier: Programming Language :: Python
Classifier: Programming Language :: Python :: 3.5
Classifier: Programming Language :: Python :: 3.6
Classifier: Programming Language :: Python :: 3.7
Classifier: Topic :: Software Development :: Libraries
Requires-Dist: cloudpickle (~=0.6.1)
Requires-Dist: gevent (~=1.3)
Requires-Dist: klein (~=17.10)
Requires-Dist: boto3 (~=1.9)
Requires-Dist: packaging (~=18.0)
Requires-Dist: typing (~=3.6)
Requires-Dist: future (~=0.17.1)
Requires-Dist: tqdm (~=4.19)
Requires-Dist: requests (~=2.20)
Requires-Dist: jsonschema (~=2.6)
Requires-Dist: matplotlib (~=2.2)
Requires-Dist: numpy (>=1.16)
Requires-Dist: simplejson (~=3.13)
Requires-Dist: ruamel.yaml (~=0.15.7)
Requires-Dist: coloredlogs (~=10.0)
Requires-Dist: scikit-learn (~=0.20.2)
Provides-Extra: mitie
Requires-Dist: mitie ; extra == 'mitie'
Provides-Extra: spacy
Requires-Dist: sklearn-crfsuite (~=0.3.6) ; extra == 'spacy'
Requires-Dist: scipy (~=1.2) ; extra == 'spacy'
Requires-Dist: spacy (<=2.0.18,>2.0) ; extra == 'spacy'
Provides-Extra: tensorflow
Requires-Dist: sklearn-crfsuite (~=0.3.6) ; extra == 'tensorflow'
Requires-Dist: scipy (~=1.2) ; extra == 'tensorflow'
Requires-Dist: tensorflow (~=1.13.0) ; extra == 'tensorflow'
Provides-Extra: test
Requires-Dist: pytest (~=3.3) ; extra == 'test'
Requires-Dist: pytest-pycodestyle (~=1.4) ; extra == 'test'
Requires-Dist: pytest-cov (~=2.5) ; extra == 'test'
Requires-Dist: pytest-twisted (<1.6) ; extra == 'test'
Requires-Dist: treq (~=17.8) ; extra == 'test'
Requires-Dist: responses (~=0.9.0) ; extra == 'test'
Requires-Dist: httpretty (~=0.9.0) ; extra == 'test'
